{"article_cms.md":"d024f6ab","algorithm_🔥刷题之探索最优解.md":"ad0fcb06","fragment_monorepo.md":"49954135","fe-utils_tool.md":"886166fc","fe-utils_git.md":"33699817","fe-utils_js工具库.md":"aa3984f2","fragment_api-no-repeat.md":"868db1db","fragment_const.md":"fc0c1a82","fragment_npm-scripts.md":"7b8790e9","fragment_react-duplicate.md":"125ab01b","fragment_var-array.md":"0b4c129e","fragment_fetch-pause.md":"d46bc09e","fragment_foreach.md":"16505d55","fragment_babel-console.md":"737f41d7","fragment_tree-shaking.md":"8f04002b","fragment_react-usestate.md":"46a80ea6","fragment_userequest.md":"91916502","fragment_nexttick.md":"b3eb1ca7","fragment_disable-debugger.md":"c36aeb5d","fragment_auto-try-catch.md":"1fc68fab","fragment_黑白.md":"2d40b353","fragment_fetch.md":"18f22ef5","fragment_return-await.md":"41722c90","fragment_settimeout.md":"d38b4e5c","fragment_微内核架构.md":"d5f61698","fragment_promise-cancel.md":"35de9aa1","fragment_react-hooks-timer.md":"66d4403b","fragment_video.md":"3791ae85","fragment_沙盒.md":"8523c3da","front-end-engineering_packagemanager.md":"19ad7b1d","front-end-engineering_css工程化.md":"c7606445","front-end-engineering_jscompatibility.md":"ff258602","front-end-engineering_modularization.md":"bb38706d","front-end-engineering_pnpm原理.md":"4502d9c1","front-end-engineering_engineering-onepage.md":"46c7db4b","front-end-engineering_webpack5-mf.md":"909d8da5","front-end-engineering_webpack常用拓展.md":"da2ea698","front-end-engineering_theme.md":"7e38fe8d","getting-started.md":"45067c8f","front-end-engineering_css 预处理器之scss.md":"ba526a7e","front-end-engineering_【完结】前端工程化.md":"299349bd","front-end-engineering_后处理器.md":"90b5948a","front-end-engineering_performance.md":"cfee43f8","html-css_html.md":"407e08a7","html-css_animation.md":"8efc43c9","html-css_css.md":"db29bf6b","html-css_drag.md":"6a8fe99f","html-css_flex.md":"3477ee34","html-css_principle.md":"251eab25","html-css_canvas-svg.md":"f0c3a714","html-css_temop.md":"154ebdea","index.md":"8031b9ed","interview_面试官：你还有问题要问我吗.md":"8b770e85","interview_算法笔试.md":"c3632b6f","js_代理与反射.md":"69e803d4","html-css_selector.md":"5b57a67e","html-css_interview.md":"dc7961d4","js_异步处理.md":"d7aefe30","react_fiber.md":"31898ce3","js_迭代器和生成器.md":"2b180ccc","react_component-communication.md":"f7d1f301","react_redux.md":"9c6b218c","react_reactrouter.md":"0dd1f5e6","react_dva.md":"1a8e0756","react_event.md":"8443dc23","react_context.md":"646258f4","react_hooks.md":"84037d0f","react_index.md":"369baa1d","react_lifecycle.md":"ebd0de84","react_react-redux-router.md":"95a49e0a","react_transition.md":"5caf45a5","react_react-interview.md":"6b46e6c2","react_render.md":"ec9c2fe4","react_utils.md":"9ef075cd","react_umi.md":"f970cd59","vue_ssr.md":"44c8a98e","vue_computed.md":"beaee277","vue_directive.md":"d6264a18","vue_nexttick.md":"07e1b377","vue_interviewer.md":"eb6ca4b2","vue_keep-alive-lru.md":"989e879c","vue_challages.md":"2e99ea46","vue_lifecycle.md":"4a37b5a0","vue_component-communication.md":"5017814a","vue_slot.md":"f4d77376","vue_diff.md":"ec6c1582","vue_v-model.md":"89a604fd","vue_vue-compile.md":"c9a45769","vue_vue-cli.md":"4817d3d9","vue_vs.md":"c2d15776","vue_vdom.md":"14b3e938","vue_reactive.md":"9f08f792","vue_vue-router.md":"eb28e208","vue_vue-interview.md":"b59bc4a2","vue_vuex.md":"9d35257d","vue_vue3-onepage.md":"42e04d6a","ts_typescript-onepage.md":"ba06297c"}
