{"article_cms.md":"5f40fdd7","fe-utils_tool.md":"02afb016","fragment_const.md":"df184bb4","algorithm_🔥刷题之探索最优解.md":"e7032cac","fragment_fetch.md":"3c342d54","fragment_foreach.md":"b16013a5","fragment_monorepo.md":"3e26ffa2","fragment_return-await.md":"a8f386f7","fe-utils_js工具库.md":"055ee444","fragment_react-hooks-timer.md":"ccaf9c07","fe-utils_git.md":"c25730b6","fragment_settimeout.md":"d7d0f6f0","fragment_react-usestate.md":"9843594d","fragment_userequest.md":"ec89e4b3","fragment_babel-console.md":"e8c9dbea","fragment_黑白.md":"0f950e92","fragment_微内核架构.md":"30f2d746","fragment_video.md":"6d42f4a4","fragment_沙盒.md":"57296ce2","front-end-engineering_packagemanager.md":"1131f158","front-end-engineering_jscompatibility.md":"1e80eee7","front-end-engineering_css工程化.md":"082ec5e6","front-end-engineering_modularization.md":"73603325","front-end-engineering_engineering-onepage.md":"b8b16d12","front-end-engineering_pnpm原理.md":"bb28f691","front-end-engineering_webpack5-mf.md":"7668c5e0","front-end-engineering_webpack常用拓展.md":"0b0a9ea0","getting-started.md":"5b1d6d30","front-end-engineering_performance.md":"9ea198b0","front-end-engineering_【完结】前端工程化.md":"040cbfa7","html-css_html.md":"fc79e6d8","html-css_animation.md":"98f8afa1","html-css_drag.md":"db27ff12","html-css_css.md":"698283ab","html-css_flex.md":"9d2fec83","html-css_canvas-svg.md":"090c2a86","html-css_principle.md":"82a78942","html-css_interview.md":"82d20af8","html-css_temop.md":"6924ec33","index.md":"5dae6488","interview_面试官：你还有问题要问我吗.md":"6741ae2c","interview_算法笔试.md":"c31d446f","html-css_selector.md":"700a826d","js_代理与反射.md":"05764afd","js_异步处理.md":"1c3ba91e","react_fiber.md":"e0ff38f4","react_redux.md":"8dbdd0e7","react_component-communication.md":"7e6d224a","js_迭代器和生成器.md":"43bc34bd","react_reactrouter.md":"9e1c08d7","react_dva.md":"7bebe393","react_event.md":"0d97f86a","react_context.md":"5ae5641d","react_hooks.md":"13c02a5c","react_lifecycle.md":"5e6f4ead","react_index.md":"041cd378","react_react-redux-router.md":"c2cb49ed","react_react-interview.md":"01db7fef","react_transition.md":"356a4dc4","react_utils.md":"d7fc2a47","react_umi.md":"836962d9","react_render.md":"052bf360","vue_ssr.md":"4869dcda","vue_computed.md":"7558a8bc","vue_directive.md":"7c9fbb5c","vue_interviewer.md":"298ebcdd","vue_keep-alive-lru.md":"43c43b0e","vue_diff.md":"868b8b98","vue_component-communication.md":"7a091cfc","vue_nexttick.md":"68669b11","vue_challages.md":"3156021f","vue_lifecycle.md":"19a74bbd","vue_slot.md":"8b249a69","vue_v-model.md":"07d94f45","vue_vs.md":"aed302b3","vue_vue-cli.md":"84df8349","vue_vue-compile.md":"8a999ef4","vue_vdom.md":"d7c89268","vue_reactive.md":"6c23d865","vue_vuex.md":"7483e325","vue_vue-router.md":"5bb0d9d7","vue_vue-interview.md":"725dae7a","vue_vue3-onepage.md":"03eaa6f5","ts_typescript-onepage.md":"e50b8d82"}
