{"article_cms.md":"febe4027","fragment_const.md":"7912886d","fragment_fetch.md":"2daf7f42","fe-utils_js工具库.md":"d32ce727","fragment_foreach.md":"88a29dbf","fragment_react-usestate.md":"5bf131a4","fe-utils_git.md":"10e0650e","fe-utils_tool.md":"8df51ff3","fragment_settimeout.md":"94745398","fragment_return-await.md":"d83c6acf","fragment_monorepo.md":"41c4c4bf","fragment_react-hooks-timer.md":"4316c8dd","fragment_黑白.md":"70e936eb","fragment_userequest.md":"429afdd5","fragment_微内核架构.md":"e7bb886c","fragment_video.md":"983dbd8e","algorithm_🔥刷题之探索最优解.md":"08d2b45b","fragment_沙盒.md":"251fef0c","fragment_babel-console.md":"06f29625","front-end-engineering_packagemanager.md":"44671e2a","front-end-engineering_jscompatibility.md":"7c4ee711","front-end-engineering_css工程化.md":"5acf41a2","front-end-engineering_modularization.md":"5346e506","front-end-engineering_pnpm原理.md":"fb65f6fd","front-end-engineering_webpack5-mf.md":"e0548a13","front-end-engineering_engineering-onepage.md":"f7ab7c24","front-end-engineering_webpack常用拓展.md":"ce82caf3","getting-started.md":"218ebdb7","front-end-engineering_【完结】前端工程化.md":"5cbdd664","front-end-engineering_performance.md":"00aae91d","html-css_flex.md":"26e89cff","html-css_html.md":"24a54fc8","html-css_drag.md":"52b77bcb","html-css_principle.md":"5aaceab3","html-css_animation.md":"7760a0b2","html-css_temop.md":"eaa1e637","index.md":"62d209f6","html-css_canvas-svg.md":"408ab790","interview_面试官：你还有问题要问我吗.md":"bee578bd","interview_算法笔试.md":"9d5a040f","html-css_css.md":"af47b6ae","js_代理与反射.md":"0a714555","react_fiber.md":"e553eacc","html-css_selector.md":"cbcd052d","react_component-communication.md":"bf8f5e8a","react_redux.md":"e8fc0667","react_dva.md":"745c4d56","react_event.md":"cca51240","react_lifecycle.md":"82e89942","react_hooks.md":"d8a0f2ed","html-css_interview.md":"3987eea2","react_react-redux-router.md":"8e351167","react_context.md":"a9758273","react_transition.md":"ab556757","react_reactrouter.md":"67b203a9","react_umi.md":"c6e33d2d","react_render.md":"22cc3562","react_utils.md":"c4bfe098","react_index.md":"054328fe","vue_ssr.md":"6cb068a3","js_迭代器和生成器.md":"63b6f379","js_异步处理.md":"17b260bc","vue_directive.md":"6ca8934a","vue_computed.md":"7d702a6d","vue_diff.md":"f5a710cd","vue_interviewer.md":"93e77ab6","vue_slot.md":"c9311a1d","vue_nexttick.md":"e3c3e5d2","vue_component-communication.md":"367bb944","vue_lifecycle.md":"dd0d1856","vue_vue-cli.md":"a14b77d9","vue_challages.md":"130469cc","vue_keep-alive-lru.md":"11ad1e73","vue_vue-compile.md":"5ae92450","vue_vs.md":"672eee72","vue_v-model.md":"825b28c9","vue_vdom.md":"52a14b62","react_react-interview.md":"1f28ca0f","vue_vue-interview.md":"985c7ee5","vue_vue-router.md":"b8ca8b88","vue_reactive.md":"dfcde8b3","vue_vuex.md":"dd3f6555","vue_vue3-onepage.md":"431aa6b1","ts_typescript-onepage.md":"5831f311"}
